horizon/__init__.py
horizon/manager.py
horizon/models.py
horizon/query.py
horizon/routers.py
horizon/settings.py
horizon/utils.py
tests/migrations/0001_initial.py
tests/migrations/__init__.py
django_horizon-1.1.2.dist-info/AUTHORS.rst
django_horizon-1.1.2.dist-info/LICENSE
django_horizon-1.1.2.dist-info/METADATA
django_horizon-1.1.2.dist-info/WHEEL
django_horizon-1.1.2.dist-info/top_level.txt
django_horizon-1.1.2.dist-info/RECORD
