Metadata-Version: 2.1
Name: django-horizon
Version: 1.1.2
Summary: Simple database sharding (horizontal partitioning) library for Django applications.
Home-page: https://github.com/uncovertruth/django-horizon
Author: UNCOVER TRUTH Inc.
Author-email: develop@uncovertruth.co.jp
License: MIT license
Keywords: django-horizon,django,sharding,horizontal partitioning,database
Platform: UNKNOWN
Classifier: Development Status :: 2 - Pre-Alpha
Classifier: Environment :: Web Environment
Classifier: Framework :: Django :: 1.11
Classifier: Framework :: Django :: 2.0
Classifier: Framework :: Django :: 2.1
Classifier: Intended Audience :: Developers
Classifier: License :: OSI Approved :: MIT License
Classifier: Natural Language :: English
Classifier: Operating System :: OS Independent
Classifier: Programming Language :: Python :: 2
Classifier: Programming Language :: Python :: 2.7
Classifier: Programming Language :: Python :: 3
Classifier: Programming Language :: Python :: 3.4
Classifier: Programming Language :: Python :: 3.5
Classifier: Programming Language :: Python :: 3.6
Classifier: Programming Language :: Python :: 3.7
Requires-Dist: Django (>=1.11)
